setup.py
slackbot_tipy/__init__.py
slackbot_tipy/bot_id.py
slackbot_tipy/slackpi.py
slackbot_tipy/testit.py
slackbot_tipy.egg-info/PKG-INFO
slackbot_tipy.egg-info/SOURCES.txt
slackbot_tipy.egg-info/dependency_links.txt
slackbot_tipy.egg-info/top_level.txt
slackbot_tipy/di/__init__.py
slackbot_tipy/di/intent.py