Metadata-Version: 1.1
Name: slackbot-tipy
Version: 0.0.516584045
Summary: Python Module for Text Intent Slackbot
Home-page: https://github.com/wray/tipy
Author: Wray Mills
Author-email: wray@wrayesian.com
License: UNKNOWN
Download-URL: https://github.com/wray/tipy/tarball/0.0.516584045
Keywords: slackbot,RPi,AWS
Platform: UNKNOWN
